jabledl/__init__.py
jabledl/_modidx.py
jabledl/args.py
jabledl/cmd.py
jabledl/core.py
jabledl/utils.py
jabledl-0.0.2.dist-info/LICENSE
jabledl-0.0.2.dist-info/METADATA
jabledl-0.0.2.dist-info/WHEEL
jabledl-0.0.2.dist-info/entry_points.txt
jabledl-0.0.2.dist-info/top_level.txt
jabledl-0.0.2.dist-info/RECORD
