Metadata-Version: 2.1
Name: jabledl
Version: 0.0.2
Summary: Jable TV 下载
Home-page: https://github.com/sidepr/jabledl
Author: sidepr
Author-email: sidepr@aliyun.com
License: Apache Software License 2.0
Keywords: jabletv jable download python
Classifier: Development Status :: 4 - Beta
Classifier: Intended Audience :: Developers
Classifier: Natural Language :: English
Classifier: Programming Language :: Python :: 3.7
Classifier: Programming Language :: Python :: 3.8
Classifier: Programming Language :: Python :: 3.9
Classifier: Programming Language :: Python :: 3.10
Classifier: License :: OSI Approved :: Apache Software License
Requires-Python: >=3.7
License-File: LICENSE
Requires-Dist: beautifulsoup4 (==4.9.3)
Requires-Dist: bleach (==5.0.1)
Requires-Dist: chardet (==4.0.0)
Requires-Dist: cloudscraper (==1.2.58)
Requires-Dist: m3u8 (==0.8.0)
Requires-Dist: pycrypto (==2.6.1)
Requires-Dist: pycryptodome (==3.4.3)
Requires-Dist: requests (==2.25.1)
Requires-Dist: tqdm (==4.64.0)
Requires-Dist: ffmpeg-python (==0.2.0)
Provides-Extra: dev
